tests/__init__.py
tests/test_store.py
tpd/__init__.py
tpd/core.py
tpd/utils.py
tpd-1.8.1.dist-info/LICENSE
tpd-1.8.1.dist-info/METADATA
tpd-1.8.1.dist-info/WHEEL
tpd-1.8.1.dist-info/entry_points.txt
tpd-1.8.1.dist-info/top_level.txt
tpd-1.8.1.dist-info/RECORD
