Metadata-Version: 2.1
Name: tpd
Version: 1.8.1
Summary: Easy saving of logs, data and plots
Home-page: https://github.com/FedeClaudi/dpl-store
Author: Federico Claudi
License: UNKNOWN
Platform: UNKNOWN
Classifier: Development Status :: 3 - Alpha
Classifier: Operating System :: POSIX :: Linux
Classifier: Operating System :: Microsoft :: Windows :: Windows 10
Classifier: Operating System :: MacOS :: MacOS X
Classifier: Programming Language :: Python
Classifier: Programming Language :: Python :: 3.6
Classifier: Programming Language :: Python :: 3.7
Classifier: Programming Language :: Python :: 3.8
Classifier: Intended Audience :: Developers
Classifier: Intended Audience :: Science/Research
Requires-Python: >=3.6
Requires-Dist: numpy
Requires-Dist: matplotlib
Requires-Dist: fcutils
Requires-Dist: myterial
Requires-Dist: pyinspect
Requires-Dist: rich
Requires-Dist: loguru
Requires-Dist: scipy
